{
  "as_of": "2026-04-27T09:09:49.630536-04:00",
  "strategy": "Khanna daily-bar copy-trade",
  "equity": 9932.48,
  "cash": 16.6,
  "allocated": 9915.88,
  "target_queue": [
    "VIG",
    "AMRZ",
    "TD",
    "IT",
    "AMZN",
    "KO",
    "MCD",
    "JPM",
    "ACI",
    "BMO"
  ],
  "positions": [
    {
      "symbol": "BMO",
      "target_weight": 0.1678,
      "current_weight": 0.168441,
      "points": 2.0449,
      "current_value": 1673.04,
      "qty": 10.995996,
      "target_value": 1666.67
    },
    {
      "symbol": "ACI",
      "target_weight": 0.1698,
      "current_weight": 0.166314,
      "points": 2.1973,
      "current_value": 1651.91,
      "qty": 99.392732,
      "target_value": 1686.54
    },
    {
      "symbol": "KO",
      "target_weight": 0.1147,
      "current_weight": 0.117826,
      "points": 1.5,
      "current_value": 1170.31,
      "qty": 15.238393,
      "target_value": 1139.26
    },
    {
      "symbol": "AMZN",
      "target_weight": 0.1024,
      "current_weight": 0.108849,
      "points": 1.25,
      "current_value": 1081.14,
      "qty": 4.062602,
      "target_value": 1017.09
    },
    {
      "symbol": "JPM",
      "target_weight": 0.1032,
      "current_weight": 0.101639,
      "points": 1.3199,
      "current_value": 1009.53,
      "qty": 3.290437,
      "target_value": 1025.03
    },
    {
      "symbol": "MCD",
      "target_weight": 0.0993,
      "current_weight": 0.095755,
      "points": 1.25,
      "current_value": 951.09,
      "qty": 3.176644,
      "target_value": 986.3
    },
    {
      "symbol": "IT",
      "target_weight": 0.0931,
      "current_weight": 0.088886,
      "points": 1.1545,
      "current_value": 882.86,
      "qty": 5.945177,
      "target_value": 924.71
    },
    {
      "symbol": "VIG",
      "target_weight": 0.0618,
      "current_weight": 0.062079,
      "points": 0.7758,
      "current_value": 616.6,
      "qty": 2.720716,
      "target_value": 613.83
    },
    {
      "symbol": "AMRZ",
      "target_weight": 0.0511,
      "current_weight": 0.05172,
      "points": 0.6585,
      "current_value": 513.7,
      "qty": 8.926211,
      "target_value": 507.55
    },
    {
      "symbol": "TD",
      "target_weight": 0.0369,
      "current_weight": 0.03682,
      "points": 0.4524,
      "current_value": 365.71,
      "qty": 3.481954,
      "target_value": 366.51
    },
    {
      "symbol": "BTC/USD",
      "target_weight": 0.0,
      "current_weight": 0.0,
      "points": 0.0,
      "current_value": 0.0,
      "qty": 0.0,
      "target_value": 0.0
    }
  ]
}
